file_darshan/__init__.py
file_darshan/ai_helper.py
file_darshan/cli.py
file_darshan/summarizer.py
filedarshan-0.1.0.dist-info/licenses/LICENSE
filedarshan-0.1.0.dist-info/METADATA
filedarshan-0.1.0.dist-info/WHEEL
filedarshan-0.1.0.dist-info/entry_points.txt
filedarshan-0.1.0.dist-info/top_level.txt
filedarshan-0.1.0.dist-info/RECORD
