Metadata-Version: 2.4
Name: filedarshan
Version: 0.1.0
Summary: A CLI tool to summarize files and folders using AI
Author-email: Mainak Chaudhuri <mainakchaudhuri671@gmail.com>
License: MIT
Requires-Python: >=3.8
License-File: LICENSE
Requires-Dist: pandas
Requires-Dist: gemini
Dynamic: license-file
